MANIFEST.in
README.rst
setup.py
djangochurch_contact/__init__.py
djangochurch_contact/forms.py
djangochurch_contact/urls.py
djangochurch_contact/views.py
djangochurch_contact.egg-info/PKG-INFO
djangochurch_contact.egg-info/SOURCES.txt
djangochurch_contact.egg-info/dependency_links.txt
djangochurch_contact.egg-info/top_level.txt
djangochurch_contact/templates/contact/form.html