Metadata-Version: 1.1
Name: djangochurch-contact
Version: 0.1
Summary: Simple contact form for Django Church sites
Home-page: https://github.com/djangochurch/djangochurch-contact
Author: Blanc Ltd
Author-email: studio@blanc.ltd.uk
License: BSD
Platform: any
Classifier: Environment :: Web Environment
Classifier: Framework :: Django
Classifier: License :: OSI Approved :: BSD License
Classifier: Operating System :: OS Independent
Classifier: Programming Language :: Python :: 2
Classifier: Programming Language :: Python :: 2.7
Classifier: Programming Language :: Python :: 3
Classifier: Programming Language :: Python :: 3.3
Classifier: Programming Language :: Python :: 3.4
Classifier: Programming Language :: Python :: 3.5
